brain/__init__.py
brain/api/__init__.py
brain/api/api.py
brain/api/base.py
brain/api/general.py
brain/api/query.py
brain/core/__init__.py
brain/core/core.py
brain/core/exceptions.py
brain/core/inspection.py
brain/data/brain.yml
brain/db/__init__.py
brain/db/modelGraph.py
brain/utils/__init__.py
brain/utils/general/__init__.py
brain/utils/general/decorators.py
brain/utils/general/general.py
marvin_brain-0.3.0.dist-info/LICENSE.md
marvin_brain-0.3.0.dist-info/METADATA
marvin_brain-0.3.0.dist-info/WHEEL
marvin_brain-0.3.0.dist-info/top_level.txt
marvin_brain-0.3.0.dist-info/RECORD
