Metadata-Version: 2.1
Name: marvin-brain
Version: 0.3.0
Summary: Core Marvin Brain for SDSS
Home-page: https://github.com/sdss/marvin_brain
Author: Brian Cherinka
Author-email: bcherinka@stsci.edu
License: BSD 3-Clause License
Project-URL: Repository, https://github.com/sdss/marvin_brain
Keywords: astronomy,software
Platform: UNKNOWN
Classifier: Intended Audience :: Science/Research
Classifier: Natural Language :: English
Classifier: Operating System :: OS Independent
Classifier: Programming Language :: Python
Classifier: Programming Language :: Python :: 3.6
Classifier: Programming Language :: Python :: 3.7
Classifier: Programming Language :: Python :: 3.8
Classifier: Topic :: Documentation :: Sphinx
Classifier: Topic :: Software Development :: Libraries :: Python Modules
Requires-Python: >=3.8
Requires-Dist: sdsstools (>=0.4.0)
Requires-Dist: sdss-access (>=2.0)
Requires-Dist: flask (>=1.1)
Requires-Dist: flask-classful (>=0.14.2)
Requires-Dist: requests (>=2.23.0)
Requires-Dist: networkx (>=2.5)
Requires-Dist: sqlalchemy (>=1.3)
Requires-Dist: pyyaml (>=5.1)
Requires-Dist: passlib (>=1.7.1)
Requires-Dist: numpy (>=1.18)
Requires-Dist: werkzeug (<2.2)
Provides-Extra: dev
Requires-Dist: Sphinx (>=3.1.0) ; extra == 'dev'
Requires-Dist: sphinx-bootstrap-theme (>=0.4.12) ; extra == 'dev'
Requires-Dist: ipython (>=7.9.0) ; extra == 'dev'
Requires-Dist: matplotlib (>=3.1.1) ; extra == 'dev'
Requires-Dist: flake8 (>=3.7.9) ; extra == 'dev'
Requires-Dist: doc8 (>=0.8.0) ; extra == 'dev'
Requires-Dist: pytest (>=5.2.2) ; extra == 'dev'
Requires-Dist: pytest-cov (>=2.8.1) ; extra == 'dev'
Requires-Dist: pytest-sugar (>=0.9.2) ; extra == 'dev'
Requires-Dist: pytest-mock (>=3.3.1) ; extra == 'dev'
Requires-Dist: isort (>=4.3.21) ; extra == 'dev'
Requires-Dist: codecov (>=2.0.15) ; extra == 'dev'
Requires-Dist: coverage[toml] (>=5.0) ; extra == 'dev'
Requires-Dist: ipdb (>=0.12.3) ; extra == 'dev'
Requires-Dist: psycopg2 (>=2.9) ; extra == 'dev'
Requires-Dist: astropy (>5.0) ; extra == 'dev'
Requires-Dist: invoke (>=1.3.0) ; extra == 'dev'
Requires-Dist: twine (>=3.1.1) ; extra == 'dev'
Requires-Dist: wheel (>=0.33.6) ; extra == 'dev'
Provides-Extra: docs
Requires-Dist: Sphinx (>=3.1.0) ; extra == 'docs'
Requires-Dist: sphinx-bootstrap-theme (>=0.4.12) ; extra == 'docs'
Provides-Extra: extra
Requires-Dist: msgpack (>=1.0) ; extra == 'extra'
Requires-Dist: msgpack-numpy (>=0.4) ; extra == 'extra'
Requires-Dist: cachecontrol (>=0.12) ; extra == 'extra'
